GregWhite-0.4.8.dist-info/DESCRIPTION.rst
GregWhite-0.4.8.dist-info/METADATA
GregWhite-0.4.8.dist-info/RECORD
GregWhite-0.4.8.dist-info/WHEEL
GregWhite-0.4.8.dist-info/entry_points.txt
GregWhite-0.4.8.dist-info/metadata.json
GregWhite-0.4.8.dist-info/top_level.txt
greg/aux_functions.py
greg/classes.py
greg/commands.py
greg/parser.py
greg/data/greg.conf
