Metadata-Version: 2.0
Name: GregWhite
Version: 0.4.8
Summary: A command-line podcast aggregator
Home-page: https://github.com/timwhite/greg
Author: Manolo Martínez, Pepie34, Timothy White
Author-email: tim@whiteitsolutions.com.au
License: GPLv3
Platform: UNKNOWN
Requires-Dist: feedparser
